contrast_image/__init__.py
contrast_image/contrast_image.py
contrast_image/histogram.py
contrast_image/quantitation.py
contrast_image/utils.py
contrast_image-0.1.6.dist-info/LICENSE
contrast_image-0.1.6.dist-info/METADATA
contrast_image-0.1.6.dist-info/WHEEL
contrast_image-0.1.6.dist-info/top_level.txt
contrast_image-0.1.6.dist-info/RECORD
