Metadata-Version: 2.1
Name: contrast_image
Version: 0.1.6
Summary: 🌈 Library to work with contrast
Home-page: https://github.com/Nguyen-Hoang-Nam/contrast-image
Author: Nguyen Hoang Nam
Author-email: nguyenhoangnam.dev@gmail.com
License: MIT
Platform: UNKNOWN
